raatk/__init__.py
raatk/__main__.py
raatk/compute.py
raatk/draw.py
raatk/feature.py
raatk/metrics.py
raatk/nr_raa_data.db
raatk/utils.py
raatk-1.2.6.dist-info/LICENSE
raatk-1.2.6.dist-info/METADATA
raatk-1.2.6.dist-info/WHEEL
raatk-1.2.6.dist-info/entry_points.txt
raatk-1.2.6.dist-info/top_level.txt
raatk-1.2.6.dist-info/zip-safe
raatk-1.2.6.dist-info/RECORD
