Metadata-Version: 2.1
Name: raatk
Version: 1.2.6
Summary: reduce amino acid toolkit
Home-page: https://github.com/huang-sh/raatk/
Author: huangsh
Author-email: hsh-me@outlook.com
License: BSD 2-Clause
Platform: UNKNOWN
Requires-Python: >=3.6
Requires-Dist: numpy (>=1.16.2)
Requires-Dist: matplotlib (>=3.1.1)
Requires-Dist: scikit-learn (>=0.22.1)
Requires-Dist: seaborn (>=0.9.0)
Requires-Dist: plotly (>=4.6.0)
